autiobooks/__init__.py
autiobooks/__main__.py
autiobooks/autiobooks.py
autiobooks/engine.py
autiobooks/post_install.py
autiobooks/voices_lang.py
autiobooks-1.1.0.dist-info/LICENSE
autiobooks-1.1.0.dist-info/METADATA
autiobooks-1.1.0.dist-info/WHEEL
autiobooks-1.1.0.dist-info/entry_points.txt
autiobooks-1.1.0.dist-info/top_level.txt
autiobooks-1.1.0.dist-info/RECORD
