Metadata-Version: 2.2
Name: autiobooks
Version: 1.1.0
Summary: Automatically convert epubs to audiobooks
Home-page: https://github.com/plusuncold/autiobooks
Author: David Nesbitt
Project-URL: Homepage, https://github.com/plusuncold/autiobooks
Project-URL: Documentation, https://github.com/plusuncold/autiobooks
Project-URL: Repository, https://github.com/plusuncold/autiobooks
Project-URL: Issues, https://github.com/plusuncold/autiobooks/issues
Requires-Python: >=3.10
License-File: LICENSE
Requires-Dist: pillow>=10.0.0
Requires-Dist: tk>=0.1.0
Requires-Dist: kokoro<0.8.0,>=0.7.9
Requires-Dist: ebooklib<0.19,>=0.18
Requires-Dist: soundfile<0.14.0,>=0.13.1
Requires-Dist: pygame<3.0.0,>=2.0.1
Requires-Dist: bs4<0.0.3,>=0.0.2
Dynamic: author
Dynamic: home-page
Dynamic: requires-python
